moschitta_routing/__init__.py
moschitta_routing/router.py
moschitta_routing/routing.py
moschitta_routing-0.1.1.dist-info/LICENSE
moschitta_routing-0.1.1.dist-info/METADATA
moschitta_routing-0.1.1.dist-info/WHEEL
moschitta_routing-0.1.1.dist-info/RECORD
