Metadata-Version: 2.1
Name: moschitta-routing
Version: 0.1.1
Summary: 
Author: Skyler Saville
Author-email: skylersaville@gmail.com
Requires-Python: >=3.11,<4.0
Classifier: Programming Language :: Python :: 3
Classifier: Programming Language :: Python :: 3.11
